{
  "graph_id": "hackatdac19__h19_debug_jtag_scope",
  "candidate_point_count": 247,
  "target_count_before_dedup": 247,
  "target_count_after_dedup": 160,
  "target_count_final": 160,
  "point_roles_distribution": {
    "auth_state": 91,
    "bounds_check": 1,
    "connection_mediation": 14,
    "control_like": 42,
    "cross_module_control": 14,
    "crypto_state": 8,
    "csr_register": 45,
    "debug_interface": 91,
    "dma_control": 1,
    "external_access": 91,
    "fuse_data": 8,
    "lifecycle_state": 22,
    "lock_state": 2,
    "mmio_register": 45,
    "mode_control": 13,
    "output_port": 7,
    "peripheral_register": 45,
    "pmp_check": 1,
    "privilege_state": 13,
    "protected_data": 8,
    "register": 23,
    "register_interface": 45,
    "reset_sensitive_state": 22,
    "resource_like": 45,
    "secret_state": 8,
    "secure_state": 13,
    "state_residue_risk": 22,
    "state_update_target": 23,
    "test_access": 91,
    "transaction_permission": 1,
    "wrapper_mediation": 14,
    "write_protection": 2
  },
  "access_roles_distribution": {
    "case_use": 73,
    "condition_use": 307,
    "cross_module_connect": 55,
    "output_drive": 7,
    "register_read": 148,
    "register_write": 180,
    "state_update": 37
  },
  "matched_rules_distribution": {
    "R1": 150,
    "R2": 2,
    "R3": 28,
    "R4": 54,
    "R5": 9,
    "R7": 3,
    "R8": 18,
    "R9": 33
  },
  "evidence_mode_distribution": {
    "explicit": 388,
    "inferred": 28
  },
  "targets_trimmed_by_repo_limit": 87,
  "targets_trimmed_by_module_limit": 0,
  "deduplicated_target_count": 0,
  "missing_source_loc_count": 0,
  "reset_branch_explicit": false,
  "warnings": []
}